asgi_app.py
mcp_auth_factory.py
mcp_auth_http_adapter.py
mcp_server_main.py
run_asgi.py
starlette_app.py
stripe_webhook.py
anayasa_mcp_module/__init__.py
anayasa_mcp_module/bireysel_client.py
anayasa_mcp_module/client.py
anayasa_mcp_module/models.py
anayasa_mcp_module/unified_client.py
bddk_mcp_module/__init__.py
bddk_mcp_module/client.py
bddk_mcp_module/models.py
bedesten_mcp_module/__init__.py
bedesten_mcp_module/client.py
bedesten_mcp_module/enums.py
bedesten_mcp_module/models.py
danistay_mcp_module/__init__.py
danistay_mcp_module/client.py
danistay_mcp_module/models.py
emsal_mcp_module/__init__.py
emsal_mcp_module/client.py
emsal_mcp_module/models.py
kik_mcp_module/__init__.py
kik_mcp_module/client_v2.py
kik_mcp_module/models_v2.py
kvkk_mcp_module/__init__.py
kvkk_mcp_module/client.py
kvkk_mcp_module/models.py
mcp_auth/__init__.py
mcp_auth/clerk_config.py
mcp_auth/middleware.py
mcp_auth/oauth.py
mcp_auth/policy.py
mcp_auth/storage.py
rekabet_mcp_module/__init__.py
rekabet_mcp_module/client.py
rekabet_mcp_module/models.py
sayistay_mcp_module/__init__.py
sayistay_mcp_module/client.py
sayistay_mcp_module/enums.py
sayistay_mcp_module/models.py
sayistay_mcp_module/unified_client.py
semantic_search/__init__.py
semantic_search/embedder.py
semantic_search/processor.py
semantic_search/vector_store.py
uyusmazlik_mcp_module/__init__.py
uyusmazlik_mcp_module/client.py
uyusmazlik_mcp_module/models.py
yargi_mcp-0.2.0.dist-info/licenses/LICENSE
yargitay_mcp_module/__init__.py
yargitay_mcp_module/client.py
yargitay_mcp_module/models.py
yargi_mcp-0.2.0.dist-info/METADATA
yargi_mcp-0.2.0.dist-info/WHEEL
yargi_mcp-0.2.0.dist-info/entry_points.txt
yargi_mcp-0.2.0.dist-info/top_level.txt
yargi_mcp-0.2.0.dist-info/RECORD
