Metadata-Version: 2.4
Name: yargi-mcp
Version: 0.2.0
Summary: MCP Server For Turkish Legal Databases
Author-email: Said Surucu <saidsrc@gmail.com>
License: MIT
Project-URL: Homepage, https://github.com/saidsurucu/yargi-mcp
Project-URL: Issues, https://github.com/saidsurucu/yargi-mcp/issues
Keywords: mcp,turkish-law,legal,yargitay,danistay,bddk,kvkk,turkish,law,court,decisions
Classifier: Development Status :: 4 - Beta
Classifier: Intended Audience :: Legal Industry
Classifier: Intended Audience :: Developers
Classifier: License :: OSI Approved :: MIT License
Classifier: Programming Language :: Python :: 3.11
Classifier: Programming Language :: Python :: 3.12
Classifier: Topic :: Software Development :: Libraries :: Python Modules
Classifier: Topic :: Text Processing :: Markup :: Markdown
Classifier: Operating System :: OS Independent
Requires-Python: >=3.11
License-File: LICENSE
Requires-Dist: beautifulsoup4>=4.13.4
Requires-Dist: httpx>=0.28.1
Requires-Dist: markitdown[pdf]>=0.1.1
Requires-Dist: pydantic>=2.11.4
Requires-Dist: aiohttp>=3.11.18
Requires-Dist: fastmcp>=2.10.5
Requires-Dist: pypdf>=5.5.0
Requires-Dist: fastapi>=0.115.14
Requires-Dist: cryptography>=44.0.0
Requires-Dist: openai>=1.0.0
Requires-Dist: numpy>=1.24.0
Provides-Extra: asgi
Requires-Dist: uvicorn[standard]>=0.30.0; extra == "asgi"
Requires-Dist: starlette>=0.37.0; extra == "asgi"
Provides-Extra: api
Requires-Dist: fastapi>=0.115.0; extra == "api"
Requires-Dist: uvicorn[standard]>=0.30.0; extra == "api"
Provides-Extra: production
Requires-Dist: gunicorn>=22.0.0; extra == "production"
Requires-Dist: uvicorn[standard]>=0.30.0; extra == "production"
Provides-Extra: saas
Requires-Dist: clerk-backend-api>=3.0.0; extra == "saas"
Requires-Dist: stripe>=9.1.0; extra == "saas"
Requires-Dist: upstash-redis>=1.1.0; extra == "saas"
Requires-Dist: tiktoken>=0.5.0; extra == "saas"
Requires-Dist: PyJWT>=2.8.0; extra == "saas"
Dynamic: license-file
